OnionPy-0.5.0.data/scripts/onion.py
OnionPy-0.5.0.dist-info/DESCRIPTION.rst
OnionPy-0.5.0.dist-info/METADATA
OnionPy-0.5.0.dist-info/RECORD
OnionPy-0.5.0.dist-info/WHEEL
OnionPy-0.5.0.dist-info/dependency_links.txt
OnionPy-0.5.0.dist-info/metadata.json
OnionPy-0.5.0.dist-info/top_level.txt
onion_py/__init__.py
onion_py/caching.py
onion_py/manager.py
onion_py/objects.py
