Metadata-Version: 2.0
Name: OnionPy
Version: 0.5.0
Summary: Python wrapper for the OnionOO tor status API
Home-page: http://github.com/duk3luk3/onion-py
Author: Lukas Erlacher
Author-email: tor@lerlacher.de
License: UNKNOWN
Platform: UNKNOWN
Requires-Dist: requests (>=2.0.0)
Provides-Extra: Results caching with django-cache
Requires-Dist: django; extra == 'Results caching with django-cache'
Provides-Extra: Results caching with memcached
Requires-Dist: pymemcache (>=1.2.1); extra == 'Results caching with memcached'
Requires-Dist: six; extra == 'Results caching with memcached'
